{
  "info": {
    "name": "Re-Pensa Tech API",
    "description": "Colección API + contrato Re-Pensa Tech. No requiere db:reset: cada ejecución crea sus propios datos (producto, reserva, chat). Ejecutar: npm run test:api",
    "schema": "https://schema.getpostman.com/json/collection/v2.1.0/collection.json"
  },
  "variable": [
    {
      "key": "token",
      "value": ""
    },
    {
      "key": "adminToken",
      "value": ""
    },
    {
      "key": "carlosToken",
      "value": ""
    },
    {
      "key": "registeredToken",
      "value": ""
    },
    {
      "key": "userId",
      "value": ""
    },
    {
      "key": "carlosUserId",
      "value": ""
    },
    {
      "key": "runId",
      "value": ""
    },
    {
      "key": "flowProductId",
      "value": ""
    },
    {
      "key": "chatId",
      "value": ""
    },
    {
      "key": "messageId",
      "value": ""
    },
    {
      "key": "appointmentMessageId",
      "value": ""
    },
    {
      "key": "newUniversityId",
      "value": ""
    },
    {
      "key": "notificationId",
      "value": ""
    },
    {
      "key": "image_url",
      "value": "https://res.cloudinary.com/demo/image/upload/sample.jpg"
    },
    {
      "key": "image_public_id",
      "value": ""
    },
    {
      "key": "registeredEmail",
      "value": ""
    },
    {
      "key": "registeredPassword",
      "value": "Register1!"
    },
    {
      "key": "tempPassword",
      "value": "TempPass2!"
    },
    {
      "key": "newUniversityDomain",
      "value": ""
    },
    {
      "key": "productName",
      "value": ""
    },
    {
      "key": "universityId",
      "value": ""
    }
  ],
  "event": [
    {
      "listen": "prerequest",
      "script": {
        "type": "text/javascript",
        "exec": [
          "if (!pm.collectionVariables.get('runId')) {",
          "  pm.collectionVariables.set('runId', Date.now().toString());",
          "}"
        ]
      }
    }
  ],
  "item": [
    {
      "name": "01 Health",
      "item": [
        {
          "name": "GET /health",
          "request": {
            "method": "GET",
            "header": [],
            "url": "{{baseUrl}}/health",
            "description": ""
          },
          "event": [
            {
              "listen": "test",
              "script": {
                "type": "text/javascript",
                "exec": [
                  "pm.test('Status 200', () => pm.response.to.have.status(200));",
                  "pm.test('Contrato health-response', () => pm.response.to.have.jsonSchema({\"type\":\"object\",\"required\":[\"status\"],\"properties\":{\"status\":{\"type\":\"string\"}}}));",
                  "pm.test('status ok', () => pm.expect(pm.response.json().status).to.eql('ok'));"
                ]
              }
            }
          ]
        }
      ]
    },
    {
      "name": "02 Auth",
      "item": [
        {
          "name": "Login Student (María)",
          "request": {
            "method": "POST",
            "header": [
              {
                "key": "Content-Type",
                "value": "application/json",
                "disabled": false
              }
            ],
            "url": "{{baseUrl}}/api/auth/login",
            "description": "",
            "body": {
              "mode": "raw",
              "raw": "{\n  \"email\": \"{{studentEmail}}\",\n  \"password\": \"{{studentPassword}}\"\n}",
              "options": {
                "raw": {
                  "language": "json"
                }
              }
            }
          },
          "event": [
            {
              "listen": "test",
              "script": {
                "type": "text/javascript",
                "exec": [
                  "pm.test('Status 200', () => pm.response.to.have.status(200));",
                  "pm.test('Contrato login-response', () => pm.response.to.have.jsonSchema({\"type\":\"object\",\"required\":[\"token\",\"user\"],\"properties\":{\"token\":{\"type\":\"string\"},\"user\":{\"type\":\"object\",\"required\":[\"id\",\"email\",\"role\"],\"properties\":{\"id\":{\"type\":\"string\"},\"university_id\":{\"type\":\"string\"},\"full_name\":{\"type\":\"string\"},\"email\":{\"type\":\"string\"},\"role\":{\"type\":\"string\",\"enum\":[\"student\",\"admin\"]}}}}}));",
                  "const body = pm.response.json();",
                  "pm.collectionVariables.set('token', body.token);",
                  "pm.collectionVariables.set('userId', body.user.id);",
                  "pm.collectionVariables.set('universityId', body.user.university_id);"
                ]
              }
            }
          ]
        },
        {
          "name": "Login Carlos",
          "request": {
            "method": "POST",
            "header": [
              {
                "key": "Content-Type",
                "value": "application/json",
                "disabled": false
              }
            ],
            "url": "{{baseUrl}}/api/auth/login",
            "description": "",
            "body": {
              "mode": "raw",
              "raw": "{\n  \"email\": \"{{carlosEmail}}\",\n  \"password\": \"{{carlosPassword}}\"\n}",
              "options": {
                "raw": {
                  "language": "json"
                }
              }
            }
          },
          "event": [
            {
              "listen": "test",
              "script": {
                "type": "text/javascript",
                "exec": [
                  "pm.test('Status 200', () => pm.response.to.have.status(200));",
                  "const body = pm.response.json();",
                  "pm.collectionVariables.set('carlosToken', body.token);",
                  "pm.collectionVariables.set('carlosUserId', body.user.id);"
                ]
              }
            }
          ]
        },
        {
          "name": "Login Admin",
          "request": {
            "method": "POST",
            "header": [
              {
                "key": "Content-Type",
                "value": "application/json",
                "disabled": false
              }
            ],
            "url": "{{baseUrl}}/api/auth/login",
            "description": "",
            "body": {
              "mode": "raw",
              "raw": "{\n  \"email\": \"{{adminEmail}}\",\n  \"password\": \"{{adminPassword}}\"\n}",
              "options": {
                "raw": {
                  "language": "json"
                }
              }
            }
          },
          "event": [
            {
              "listen": "test",
              "script": {
                "type": "text/javascript",
                "exec": [
                  "pm.test('Status 200', () => pm.response.to.have.status(200));",
                  "pm.collectionVariables.set('adminToken', pm.response.json().token);"
                ]
              }
            }
          ]
        },
        {
          "name": "Login inválido",
          "request": {
            "method": "POST",
            "header": [
              {
                "key": "Content-Type",
                "value": "application/json",
                "disabled": false
              }
            ],
            "url": "{{baseUrl}}/api/auth/login",
            "description": "",
            "body": {
              "mode": "raw",
              "raw": "{\n  \"email\": \"{{studentEmail}}\",\n  \"password\": \"wrong-password\"\n}",
              "options": {
                "raw": {
                  "language": "json"
                }
              }
            }
          },
          "event": [
            {
              "listen": "test",
              "script": {
                "type": "text/javascript",
                "exec": [
                  "pm.test('Status 401', () => pm.response.to.have.status(401));",
                  "pm.test('Contrato api-error', () => pm.response.to.have.jsonSchema({\"type\":\"object\",\"required\":[\"message\"],\"properties\":{\"message\":{\"type\":\"string\"}}}));"
                ]
              }
            }
          ]
        },
        {
          "name": "Register usuario único",
          "request": {
            "method": "POST",
            "header": [
              {
                "key": "Content-Type",
                "value": "application/json",
                "disabled": false
              }
            ],
            "url": "{{baseUrl}}/api/auth/register",
            "description": "",
            "body": {
              "mode": "raw",
              "raw": "{\n  \"university_id\": \"{{universityId}}\",\n  \"full_name\": \"Usuario Prueba API\",\n  \"email\": \"{{registeredEmail}}\",\n  \"password\": \"{{registeredPassword}}\"\n}",
              "options": {
                "raw": {
                  "language": "json"
                }
              }
            }
          },
          "event": [
            {
              "listen": "prerequest",
              "script": {
                "type": "text/javascript",
                "exec": [
                  "const email = `test+${pm.collectionVariables.get('runId')}@uniempresarial.edu.co`;",
                  "pm.collectionVariables.set('registeredEmail', email);"
                ]
              }
            },
            {
              "listen": "test",
              "script": {
                "type": "text/javascript",
                "exec": [
                  "pm.test('Status 201', () => pm.response.to.have.status(201));",
                  "pm.test('Contrato register-response', () => pm.response.to.have.jsonSchema({\"type\":\"object\",\"required\":[\"message\",\"user\"],\"properties\":{\"message\":{\"type\":\"string\"},\"user\":{\"type\":\"object\",\"required\":[\"id\",\"email\",\"role\"],\"properties\":{\"id\":{\"type\":\"string\"},\"email\":{\"type\":\"string\"},\"role\":{\"type\":\"string\"}}}}}));",
                  "pm.collectionVariables.set('registeredUserId', pm.response.json().user.id);"
                ]
              }
            }
          ]
        },
        {
          "name": "Login usuario registrado",
          "request": {
            "method": "POST",
            "header": [
              {
                "key": "Content-Type",
                "value": "application/json",
                "disabled": false
              }
            ],
            "url": "{{baseUrl}}/api/auth/login",
            "description": "",
            "body": {
              "mode": "raw",
              "raw": "{\n  \"email\": \"{{registeredEmail}}\",\n  \"password\": \"{{registeredPassword}}\"\n}",
              "options": {
                "raw": {
                  "language": "json"
                }
              }
            }
          },
          "event": [
            {
              "listen": "test",
              "script": {
                "type": "text/javascript",
                "exec": [
                  "pm.test('Status 200', () => pm.response.to.have.status(200));",
                  "pm.collectionVariables.set('registeredToken', pm.response.json().token);"
                ]
              }
            }
          ]
        },
        {
          "name": "Change password (nueva)",
          "request": {
            "method": "PATCH",
            "header": [
              {
                "key": "Content-Type",
                "value": "application/json",
                "disabled": false
              }
            ],
            "url": "{{baseUrl}}/api/auth/change-password",
            "description": "",
            "body": {
              "mode": "raw",
              "raw": "{\n  \"current_password\": \"{{registeredPassword}}\",\n  \"new_password\": \"{{tempPassword}}\"\n}",
              "options": {
                "raw": {
                  "language": "json"
                }
              }
            },
            "auth": {
              "type": "bearer",
              "bearer": [
                {
                  "key": "token",
                  "value": "{{registeredToken}}",
                  "type": "string"
                }
              ]
            }
          },
          "event": [
            {
              "listen": "test",
              "script": {
                "type": "text/javascript",
                "exec": [
                  "pm.test('Status 200', () => pm.response.to.have.status(200));",
                  "pm.test('mensaje de éxito', () => pm.expect(pm.response.json().message).to.be.a('string'));"
                ]
              }
            }
          ]
        },
        {
          "name": "Change password (revertir)",
          "request": {
            "method": "PATCH",
            "header": [
              {
                "key": "Content-Type",
                "value": "application/json",
                "disabled": false
              }
            ],
            "url": "{{baseUrl}}/api/auth/change-password",
            "description": "",
            "body": {
              "mode": "raw",
              "raw": "{\n  \"current_password\": \"{{tempPassword}}\",\n  \"new_password\": \"{{registeredPassword}}\"\n}",
              "options": {
                "raw": {
                  "language": "json"
                }
              }
            },
            "auth": {
              "type": "bearer",
              "bearer": [
                {
                  "key": "token",
                  "value": "{{registeredToken}}",
                  "type": "string"
                }
              ]
            }
          },
          "event": [
            {
              "listen": "test",
              "script": {
                "type": "text/javascript",
                "exec": [
                  "pm.test('Status 200', () => pm.response.to.have.status(200));"
                ]
              }
            }
          ]
        }
      ]
    },
    {
      "name": "03 Universities",
      "item": [
        {
          "name": "GET /api/universities",
          "request": {
            "method": "GET",
            "header": [],
            "url": "{{baseUrl}}/api/universities",
            "description": ""
          },
          "event": [
            {
              "listen": "test",
              "script": {
                "type": "text/javascript",
                "exec": [
                  "pm.test('Status 200', () => pm.response.to.have.status(200));",
                  "pm.test(\"es array\", () => pm.expect(pm.response.json()).to.be.an(\"array\"));",
                  "pm.test(\"hay al menos una universidad\", () => pm.expect(pm.response.json().length).to.be.above(0));",
                  "pm.test('Contrato university', () => {",
                  "  const first = pm.response.json()[0];",
                  "  pm.expect(first).to.have.property('id');",
                  "  pm.expect(first).to.have.property('email_domain');",
                  "  if (!pm.collectionVariables.get('universityId')) {",
                  "    pm.collectionVariables.set('universityId', first.id);",
                  "  }",
                  "});"
                ]
              }
            }
          ]
        },
        {
          "name": "POST /api/universities (admin)",
          "request": {
            "method": "POST",
            "header": [
              {
                "key": "Content-Type",
                "value": "application/json",
                "disabled": false
              }
            ],
            "url": "{{baseUrl}}/api/universities",
            "description": "",
            "body": {
              "mode": "raw",
              "raw": "{\n  \"name\": \"Universidad Prueba API\",\n  \"email_domain\": \"{{newUniversityDomain}}\",\n  \"subscription_start\": \"2026-01-01T00:00:00.000Z\",\n  \"subscription_end\": \"2026-12-31T23:59:59.999Z\"\n}",
              "options": {
                "raw": {
                  "language": "json"
                }
              }
            },
            "auth": {
              "type": "bearer",
              "bearer": [
                {
                  "key": "token",
                  "value": "{{adminToken}}",
                  "type": "string"
                }
              ]
            }
          },
          "event": [
            {
              "listen": "prerequest",
              "script": {
                "type": "text/javascript",
                "exec": [
                  "const runId = pm.collectionVariables.get('runId');",
                  "pm.collectionVariables.set('newUniversityDomain', `testuni-${runId}.edu.co`);"
                ]
              }
            },
            {
              "listen": "test",
              "script": {
                "type": "text/javascript",
                "exec": [
                  "pm.test('Status 201', () => pm.response.to.have.status(201));",
                  "pm.test('Contrato university', () => pm.response.to.have.jsonSchema({\"type\":\"object\",\"required\":[\"id\",\"name\",\"email_domain\",\"subscription_status\"],\"properties\":{\"id\":{\"type\":\"string\"},\"name\":{\"type\":\"string\"},\"email_domain\":{\"type\":\"string\"},\"subscription_status\":{\"type\":\"string\",\"enum\":[\"active\",\"inactive\",\"expired\"]}}}));",
                  "pm.collectionVariables.set('newUniversityId', pm.response.json().id);"
                ]
              }
            }
          ]
        },
        {
          "name": "PATCH /api/universities/:id/status (admin)",
          "request": {
            "method": "PATCH",
            "header": [
              {
                "key": "Content-Type",
                "value": "application/json",
                "disabled": false
              }
            ],
            "url": "{{baseUrl}}/api/universities/{{newUniversityId}}/status",
            "description": "",
            "body": {
              "mode": "raw",
              "raw": "{\n  \"status\": \"inactive\"\n}",
              "options": {
                "raw": {
                  "language": "json"
                }
              }
            },
            "auth": {
              "type": "bearer",
              "bearer": [
                {
                  "key": "token",
                  "value": "{{adminToken}}",
                  "type": "string"
                }
              ]
            }
          },
          "event": [
            {
              "listen": "test",
              "script": {
                "type": "text/javascript",
                "exec": [
                  "pm.test('Status 200', () => pm.response.to.have.status(200));",
                  "pm.test('estado actualizado', () => pm.expect(pm.response.json().subscription_status).to.eql('inactive'));"
                ]
              }
            }
          ]
        }
      ]
    },
    {
      "name": "04 Upload",
      "item": [
        {
          "name": "POST /api/upload/product-image",
          "request": {
            "method": "POST",
            "header": [],
            "url": "{{baseUrl}}/api/upload/product-image",
            "description": "",
            "body": {
              "mode": "formdata",
              "formdata": [
                {
                  "key": "image",
                  "type": "file",
                  "src": "postman/fixtures/sample.jpg"
                }
              ]
            },
            "auth": {
              "type": "bearer",
              "bearer": [
                {
                  "key": "token",
                  "value": "{{token}}",
                  "type": "string"
                }
              ]
            }
          },
          "event": [
            {
              "listen": "prerequest",
              "script": {
                "type": "text/javascript",
                "exec": [
                  "if (pm.environment.get('skipExternal') === 'true') {",
                  "  pm.execution.skipRequest();",
                  "}"
                ]
              }
            },
            {
              "listen": "test",
              "script": {
                "type": "text/javascript",
                "exec": [
                  "pm.test('Status 201', () => pm.response.to.have.status(201));",
                  "const body = pm.response.json();",
                  "pm.collectionVariables.set('image_url', body.image_url);",
                  "pm.collectionVariables.set('image_public_id', body.image_public_id || '');",
                  "pm.test('image_url presente', () => pm.expect(body.image_url).to.be.a('string'));"
                ]
              }
            }
          ]
        }
      ]
    },
    {
      "name": "05 Products",
      "item": [
        {
          "name": "POST /api/products (Carlos)",
          "request": {
            "method": "POST",
            "header": [
              {
                "key": "Content-Type",
                "value": "application/json",
                "disabled": false
              }
            ],
            "url": "{{baseUrl}}/api/products",
            "description": "",
            "body": {
              "mode": "raw",
              "raw": "{\n  \"name\": \"{{productName}}\",\n  \"description\": \"Producto creado por pruebas Newman\",\n  \"price\": 12000,\n  \"is_donation\": false,\n  \"category\": \"microcontrollers\",\n  \"condition\": \"good\",\n  \"image_url\": \"{{image_url}}\",\n  \"image_public_id\": \"{{image_public_id}}\"\n}",
              "options": {
                "raw": {
                  "language": "json"
                }
              }
            },
            "auth": {
              "type": "bearer",
              "bearer": [
                {
                  "key": "token",
                  "value": "{{carlosToken}}",
                  "type": "string"
                }
              ]
            }
          },
          "event": [
            {
              "listen": "prerequest",
              "script": {
                "type": "text/javascript",
                "exec": [
                  "const runId = pm.collectionVariables.get('runId');",
                  "pm.collectionVariables.set('productName', `Producto API ${runId}`);"
                ]
              }
            },
            {
              "listen": "test",
              "script": {
                "type": "text/javascript",
                "exec": [
                  "pm.test('Status 201', () => pm.response.to.have.status(201));",
                  "pm.test('Contrato product', () => pm.response.to.have.jsonSchema({\"type\":\"object\",\"required\":[\"id\",\"name\",\"status\",\"seller_id\"],\"properties\":{\"id\":{\"type\":\"string\"},\"seller_id\":{\"type\":\"string\"},\"university_id\":{\"type\":\"string\"},\"name\":{\"type\":\"string\"},\"description\":{\"type\":\"string\"},\"price\":{\"type\":\"number\"},\"is_donation\":{\"type\":\"boolean\"},\"category\":{\"type\":\"string\"},\"condition\":{\"type\":\"string\"},\"status\":{\"type\":\"string\",\"enum\":[\"available\",\"reserved\",\"sold\"]}}}));",
                  "pm.collectionVariables.set('flowProductId', pm.response.json().id);"
                ]
              }
            }
          ]
        },
        {
          "name": "GET /api/products/:id (flujo)",
          "request": {
            "method": "GET",
            "header": [],
            "url": "{{baseUrl}}/api/products/{{flowProductId}}",
            "description": "",
            "auth": {
              "type": "bearer",
              "bearer": [
                {
                  "key": "token",
                  "value": "{{token}}",
                  "type": "string"
                }
              ]
            }
          },
          "event": [
            {
              "listen": "test",
              "script": {
                "type": "text/javascript",
                "exec": [
                  "pm.test('Status 200', () => pm.response.to.have.status(200));",
                  "pm.test('Contrato product', () => pm.response.to.have.jsonSchema({\"type\":\"object\",\"required\":[\"id\",\"name\",\"status\",\"seller_id\"],\"properties\":{\"id\":{\"type\":\"string\"},\"seller_id\":{\"type\":\"string\"},\"university_id\":{\"type\":\"string\"},\"name\":{\"type\":\"string\"},\"description\":{\"type\":\"string\"},\"price\":{\"type\":\"number\"},\"is_donation\":{\"type\":\"boolean\"},\"category\":{\"type\":\"string\"},\"condition\":{\"type\":\"string\"},\"status\":{\"type\":\"string\",\"enum\":[\"available\",\"reserved\",\"sold\"]}}}));",
                  "pm.test('producto del flujo', () => pm.expect(pm.response.json().id).to.eql(pm.collectionVariables.get('flowProductId')));"
                ]
              }
            }
          ]
        },
        {
          "name": "GET /api/products",
          "request": {
            "method": "GET",
            "header": [],
            "url": "{{baseUrl}}/api/products",
            "description": "",
            "auth": {
              "type": "bearer",
              "bearer": [
                {
                  "key": "token",
                  "value": "{{token}}",
                  "type": "string"
                }
              ]
            }
          },
          "event": [
            {
              "listen": "test",
              "script": {
                "type": "text/javascript",
                "exec": [
                  "pm.test('Status 200', () => pm.response.to.have.status(200));",
                  "pm.test(\"es array\", () => pm.expect(pm.response.json()).to.be.an(\"array\"));"
                ]
              }
            }
          ]
        },
        {
          "name": "GET /api/products/mine",
          "request": {
            "method": "GET",
            "header": [],
            "url": "{{baseUrl}}/api/products/mine",
            "description": "",
            "auth": {
              "type": "bearer",
              "bearer": [
                {
                  "key": "token",
                  "value": "{{token}}",
                  "type": "string"
                }
              ]
            }
          },
          "event": [
            {
              "listen": "test",
              "script": {
                "type": "text/javascript",
                "exec": [
                  "pm.test('Status 200', () => pm.response.to.have.status(200));"
                ]
              }
            }
          ]
        },
        {
          "name": "POST /api/products/generate-description",
          "request": {
            "method": "POST",
            "header": [],
            "url": "{{baseUrl}}/api/products/generate-description",
            "description": "",
            "body": {
              "mode": "formdata",
              "formdata": [
                {
                  "key": "image",
                  "type": "file",
                  "src": "postman/fixtures/sample.jpg"
                }
              ]
            },
            "auth": {
              "type": "bearer",
              "bearer": [
                {
                  "key": "token",
                  "value": "{{token}}",
                  "type": "string"
                }
              ]
            }
          },
          "event": [
            {
              "listen": "prerequest",
              "script": {
                "type": "text/javascript",
                "exec": [
                  "if (pm.environment.get('skipExternal') === 'true') {",
                  "  pm.execution.skipRequest();",
                  "}",
                  "if (pm.environment.get('skipGroq') === 'true') {",
                  "  pm.execution.skipRequest();",
                  "}"
                ]
              }
            },
            {
              "listen": "test",
              "script": {
                "type": "text/javascript",
                "exec": [
                  "pm.test('Status 200', () => pm.response.to.have.status(200));",
                  "pm.test('description generada', () => pm.expect(pm.response.json().description).to.be.a('string'));"
                ]
              }
            }
          ]
        },
        {
          "name": "GET /api/products/:id sin token",
          "request": {
            "method": "GET",
            "header": [],
            "url": "{{baseUrl}}/api/products/{{flowProductId}}",
            "description": ""
          },
          "event": [
            {
              "listen": "test",
              "script": {
                "type": "text/javascript",
                "exec": [
                  "pm.test('Status 401', () => pm.response.to.have.status(401));",
                  "pm.test('Contrato api-error', () => pm.response.to.have.jsonSchema({\"type\":\"object\",\"required\":[\"message\"],\"properties\":{\"message\":{\"type\":\"string\"}}}));"
                ]
              }
            }
          ]
        }
      ]
    },
    {
      "name": "06 Reservations",
      "item": [
        {
          "name": "POST /api/reservations producto propio (400)",
          "request": {
            "method": "POST",
            "header": [
              {
                "key": "Content-Type",
                "value": "application/json",
                "disabled": false
              }
            ],
            "url": "{{baseUrl}}/api/reservations",
            "description": "",
            "body": {
              "mode": "raw",
              "raw": "{\n  \"product_id\": \"{{flowProductId}}\"\n}",
              "options": {
                "raw": {
                  "language": "json"
                }
              }
            },
            "auth": {
              "type": "bearer",
              "bearer": [
                {
                  "key": "token",
                  "value": "{{carlosToken}}",
                  "type": "string"
                }
              ]
            }
          },
          "event": [
            {
              "listen": "test",
              "script": {
                "type": "text/javascript",
                "exec": [
                  "pm.test('Status 400', () => pm.response.to.have.status(400));",
                  "pm.test('Contrato api-error', () => pm.response.to.have.jsonSchema({\"type\":\"object\",\"required\":[\"message\"],\"properties\":{\"message\":{\"type\":\"string\"}}}));"
                ]
              }
            }
          ]
        },
        {
          "name": "POST /api/reservations (María)",
          "request": {
            "method": "POST",
            "header": [
              {
                "key": "Content-Type",
                "value": "application/json",
                "disabled": false
              }
            ],
            "url": "{{baseUrl}}/api/reservations",
            "description": "",
            "body": {
              "mode": "raw",
              "raw": "{\n  \"product_id\": \"{{flowProductId}}\"\n}",
              "options": {
                "raw": {
                  "language": "json"
                }
              }
            },
            "auth": {
              "type": "bearer",
              "bearer": [
                {
                  "key": "token",
                  "value": "{{token}}",
                  "type": "string"
                }
              ]
            }
          },
          "event": [
            {
              "listen": "test",
              "script": {
                "type": "text/javascript",
                "exec": [
                  "pm.test('Status 201', () => pm.response.to.have.status(201));",
                  "pm.test('Contrato reservation', () => pm.response.to.have.jsonSchema({\"type\":\"object\",\"required\":[\"id\",\"product_id\",\"buyer_id\",\"status\"],\"properties\":{\"id\":{\"type\":\"string\"},\"product_id\":{\"type\":\"string\"},\"buyer_id\":{\"type\":\"string\"},\"fee_paid\":{\"type\":\"number\"},\"status\":{\"type\":\"string\",\"enum\":[\"active\",\"completed\",\"expired\"]}}}));"
                ]
              }
            }
          ]
        },
        {
          "name": "GET /api/reservations",
          "request": {
            "method": "GET",
            "header": [],
            "url": "{{baseUrl}}/api/reservations",
            "description": "",
            "auth": {
              "type": "bearer",
              "bearer": [
                {
                  "key": "token",
                  "value": "{{token}}",
                  "type": "string"
                }
              ]
            }
          },
          "event": [
            {
              "listen": "test",
              "script": {
                "type": "text/javascript",
                "exec": [
                  "pm.test('Status 200', () => pm.response.to.have.status(200));",
                  "pm.test(\"es array\", () => pm.expect(pm.response.json()).to.be.an(\"array\"));",
                  "pm.test('incluye reserva del flujo', () => {",
                  "  const ids = pm.response.json().map((r) => r.product_id);",
                  "  pm.expect(ids).to.include(pm.collectionVariables.get('flowProductId'));",
                  "});"
                ]
              }
            }
          ]
        }
      ]
    },
    {
      "name": "07 Chats",
      "item": [
        {
          "name": "POST /api/chats",
          "request": {
            "method": "POST",
            "header": [
              {
                "key": "Content-Type",
                "value": "application/json",
                "disabled": false
              }
            ],
            "url": "{{baseUrl}}/api/chats",
            "description": "",
            "body": {
              "mode": "raw",
              "raw": "{\n  \"product_id\": \"{{flowProductId}}\"\n}",
              "options": {
                "raw": {
                  "language": "json"
                }
              }
            },
            "auth": {
              "type": "bearer",
              "bearer": [
                {
                  "key": "token",
                  "value": "{{token}}",
                  "type": "string"
                }
              ]
            }
          },
          "event": [
            {
              "listen": "test",
              "script": {
                "type": "text/javascript",
                "exec": [
                  "pm.test('Status 201', () => pm.response.to.have.status(201));",
                  "pm.test('Contrato chat', () => pm.response.to.have.jsonSchema({\"type\":\"object\",\"required\":[\"id\",\"product_id\",\"buyer_id\",\"seller_id\",\"status\"],\"properties\":{\"id\":{\"type\":\"string\"},\"product_id\":{\"type\":\"string\"},\"buyer_id\":{\"type\":\"string\"},\"seller_id\":{\"type\":\"string\"},\"status\":{\"type\":\"string\",\"enum\":[\"open\",\"delivery_confirmed\"]}}}));",
                  "pm.collectionVariables.set('chatId', pm.response.json().id);"
                ]
              }
            }
          ]
        },
        {
          "name": "GET /api/chats",
          "request": {
            "method": "GET",
            "header": [],
            "url": "{{baseUrl}}/api/chats",
            "description": "",
            "auth": {
              "type": "bearer",
              "bearer": [
                {
                  "key": "token",
                  "value": "{{token}}",
                  "type": "string"
                }
              ]
            }
          },
          "event": [
            {
              "listen": "test",
              "script": {
                "type": "text/javascript",
                "exec": [
                  "pm.test('Status 200', () => pm.response.to.have.status(200));"
                ]
              }
            }
          ]
        },
        {
          "name": "GET /api/chats/:id",
          "request": {
            "method": "GET",
            "header": [],
            "url": "{{baseUrl}}/api/chats/{{chatId}}",
            "description": "",
            "auth": {
              "type": "bearer",
              "bearer": [
                {
                  "key": "token",
                  "value": "{{token}}",
                  "type": "string"
                }
              ]
            }
          },
          "event": [
            {
              "listen": "test",
              "script": {
                "type": "text/javascript",
                "exec": [
                  "pm.test('Status 200', () => pm.response.to.have.status(200));",
                  "pm.test('Contrato chat', () => pm.response.to.have.jsonSchema({\"type\":\"object\",\"required\":[\"id\",\"product_id\",\"buyer_id\",\"seller_id\",\"status\"],\"properties\":{\"id\":{\"type\":\"string\"},\"product_id\":{\"type\":\"string\"},\"buyer_id\":{\"type\":\"string\"},\"seller_id\":{\"type\":\"string\"},\"status\":{\"type\":\"string\",\"enum\":[\"open\",\"delivery_confirmed\"]}}}));"
                ]
              }
            }
          ]
        },
        {
          "name": "POST mensaje texto",
          "request": {
            "method": "POST",
            "header": [
              {
                "key": "Content-Type",
                "value": "application/json",
                "disabled": false
              }
            ],
            "url": "{{baseUrl}}/api/chats/{{chatId}}/messages",
            "description": "",
            "body": {
              "mode": "raw",
              "raw": "{\n  \"type\": \"text\",\n  \"content\": \"Hola, ¿sigue disponible?\"\n}",
              "options": {
                "raw": {
                  "language": "json"
                }
              }
            },
            "auth": {
              "type": "bearer",
              "bearer": [
                {
                  "key": "token",
                  "value": "{{token}}",
                  "type": "string"
                }
              ]
            }
          },
          "event": [
            {
              "listen": "test",
              "script": {
                "type": "text/javascript",
                "exec": [
                  "pm.test('Status 201', () => pm.response.to.have.status(201));",
                  "pm.test('Contrato message', () => pm.response.to.have.jsonSchema({\"type\":\"object\",\"required\":[\"id\",\"chat_id\",\"sender_id\",\"type\"],\"properties\":{\"id\":{\"type\":\"string\"},\"chat_id\":{\"type\":\"string\"},\"sender_id\":{\"type\":\"string\"},\"type\":{\"type\":\"string\",\"enum\":[\"text\",\"appointment\"]}}}));",
                  "pm.collectionVariables.set('messageId', pm.response.json().id);"
                ]
              }
            }
          ]
        },
        {
          "name": "GET /api/chats/:id/messages",
          "request": {
            "method": "GET",
            "header": [],
            "url": "{{baseUrl}}/api/chats/{{chatId}}/messages",
            "description": "",
            "auth": {
              "type": "bearer",
              "bearer": [
                {
                  "key": "token",
                  "value": "{{token}}",
                  "type": "string"
                }
              ]
            }
          },
          "event": [
            {
              "listen": "test",
              "script": {
                "type": "text/javascript",
                "exec": [
                  "pm.test('Status 200', () => pm.response.to.have.status(200));",
                  "pm.test(\"mensajes array\", () => pm.expect(pm.response.json()).to.be.an(\"array\"));"
                ]
              }
            }
          ]
        },
        {
          "name": "POST mensaje appointment",
          "request": {
            "method": "POST",
            "header": [
              {
                "key": "Content-Type",
                "value": "application/json",
                "disabled": false
              }
            ],
            "url": "{{baseUrl}}/api/chats/{{chatId}}/messages",
            "description": "",
            "body": {
              "mode": "raw",
              "raw": "{\n  \"type\": \"appointment\",\n  \"appointment\": {\n    \"day\": \"Lunes 10\",\n    \"time\": \"10:00\",\n    \"location\": \"Biblioteca central\"\n  }\n}",
              "options": {
                "raw": {
                  "language": "json"
                }
              }
            },
            "auth": {
              "type": "bearer",
              "bearer": [
                {
                  "key": "token",
                  "value": "{{token}}",
                  "type": "string"
                }
              ]
            }
          },
          "event": [
            {
              "listen": "test",
              "script": {
                "type": "text/javascript",
                "exec": [
                  "pm.test('Status 201', () => pm.response.to.have.status(201));",
                  "pm.test('Contrato message', () => pm.response.to.have.jsonSchema({\"type\":\"object\",\"required\":[\"id\",\"chat_id\",\"sender_id\",\"type\"],\"properties\":{\"id\":{\"type\":\"string\"},\"chat_id\":{\"type\":\"string\"},\"sender_id\":{\"type\":\"string\"},\"type\":{\"type\":\"string\",\"enum\":[\"text\",\"appointment\"]}}}));",
                  "pm.collectionVariables.set('appointmentMessageId', pm.response.json().id);"
                ]
              }
            }
          ]
        },
        {
          "name": "PATCH appointment accept (Carlos)",
          "request": {
            "method": "PATCH",
            "header": [
              {
                "key": "Content-Type",
                "value": "application/json",
                "disabled": false
              }
            ],
            "url": "{{baseUrl}}/api/chats/{{chatId}}/messages/{{appointmentMessageId}}/appointment",
            "description": "",
            "body": {
              "mode": "raw",
              "raw": "{\n  \"action\": \"accept\"\n}",
              "options": {
                "raw": {
                  "language": "json"
                }
              }
            },
            "auth": {
              "type": "bearer",
              "bearer": [
                {
                  "key": "token",
                  "value": "{{carlosToken}}",
                  "type": "string"
                }
              ]
            }
          },
          "event": [
            {
              "listen": "test",
              "script": {
                "type": "text/javascript",
                "exec": [
                  "pm.test('Status 200', () => pm.response.to.have.status(200));"
                ]
              }
            }
          ]
        },
        {
          "name": "PATCH confirm-delivery (Carlos)",
          "request": {
            "method": "PATCH",
            "header": [
              {
                "key": "Content-Type",
                "value": "application/json",
                "disabled": false
              }
            ],
            "url": "{{baseUrl}}/api/chats/{{chatId}}/confirm-delivery",
            "description": "",
            "auth": {
              "type": "bearer",
              "bearer": [
                {
                  "key": "token",
                  "value": "{{carlosToken}}",
                  "type": "string"
                }
              ]
            }
          },
          "event": [
            {
              "listen": "test",
              "script": {
                "type": "text/javascript",
                "exec": [
                  "pm.test('Status 200', () => pm.response.to.have.status(200));",
                  "pm.test('entrega confirmada', () => pm.expect(pm.response.json().message).to.include('Entrega confirmada'));"
                ]
              }
            }
          ]
        }
      ]
    },
    {
      "name": "08 Transactions",
      "item": [
        {
          "name": "GET /api/transactions (María)",
          "request": {
            "method": "GET",
            "header": [],
            "url": "{{baseUrl}}/api/transactions",
            "description": "",
            "auth": {
              "type": "bearer",
              "bearer": [
                {
                  "key": "token",
                  "value": "{{token}}",
                  "type": "string"
                }
              ]
            }
          },
          "event": [
            {
              "listen": "test",
              "script": {
                "type": "text/javascript",
                "exec": [
                  "pm.test('Status 200', () => pm.response.to.have.status(200));",
                  "pm.test(\"historial compras\", () => pm.expect(pm.response.json().length).to.be.above(0));"
                ]
              }
            }
          ]
        },
        {
          "name": "GET /api/transactions (Carlos)",
          "request": {
            "method": "GET",
            "header": [],
            "url": "{{baseUrl}}/api/transactions",
            "description": "",
            "auth": {
              "type": "bearer",
              "bearer": [
                {
                  "key": "token",
                  "value": "{{carlosToken}}",
                  "type": "string"
                }
              ]
            }
          },
          "event": [
            {
              "listen": "test",
              "script": {
                "type": "text/javascript",
                "exec": [
                  "pm.test('Status 200', () => pm.response.to.have.status(200));",
                  "pm.test(\"historial ventas\", () => pm.expect(pm.response.json().length).to.be.above(0));"
                ]
              }
            }
          ]
        }
      ]
    },
    {
      "name": "09 Notifications",
      "item": [
        {
          "name": "GET /api/notifications",
          "request": {
            "method": "GET",
            "header": [],
            "url": "{{baseUrl}}/api/notifications",
            "description": "",
            "auth": {
              "type": "bearer",
              "bearer": [
                {
                  "key": "token",
                  "value": "{{token}}",
                  "type": "string"
                }
              ]
            }
          },
          "event": [
            {
              "listen": "test",
              "script": {
                "type": "text/javascript",
                "exec": [
                  "pm.test('Status 200', () => pm.response.to.have.status(200));",
                  "pm.test('Contrato notifications-response', () => {",
                  "  const payload = pm.response.json();",
                  "  pm.expect(payload).to.have.property('notifications');",
                  "  pm.expect(payload).to.have.property('unread');",
                  "  pm.expect(payload.notifications).to.be.an('array');",
                  "});",
                  "const notifPayload = pm.response.json();",
                  "if (notifPayload.notifications.length > 0) {",
                  "  pm.collectionVariables.set('notificationId', notifPayload.notifications[0].id);",
                  "}"
                ]
              }
            }
          ]
        },
        {
          "name": "PATCH /api/notifications/read-all",
          "request": {
            "method": "PATCH",
            "header": [
              {
                "key": "Content-Type",
                "value": "application/json",
                "disabled": false
              }
            ],
            "url": "{{baseUrl}}/api/notifications/read-all",
            "description": "",
            "auth": {
              "type": "bearer",
              "bearer": [
                {
                  "key": "token",
                  "value": "{{token}}",
                  "type": "string"
                }
              ]
            }
          },
          "event": [
            {
              "listen": "test",
              "script": {
                "type": "text/javascript",
                "exec": [
                  "pm.test('Status 200', () => pm.response.to.have.status(200));"
                ]
              }
            }
          ]
        },
        {
          "name": "PATCH /api/notifications/:id/read",
          "request": {
            "method": "PATCH",
            "header": [
              {
                "key": "Content-Type",
                "value": "application/json",
                "disabled": false
              }
            ],
            "url": "{{baseUrl}}/api/notifications/{{notificationId}}/read",
            "description": "",
            "auth": {
              "type": "bearer",
              "bearer": [
                {
                  "key": "token",
                  "value": "{{token}}",
                  "type": "string"
                }
              ]
            }
          },
          "event": [
            {
              "listen": "prerequest",
              "script": {
                "type": "text/javascript",
                "exec": [
                  "if (!pm.collectionVariables.get('notificationId')) {",
                  "  pm.execution.skipRequest();",
                  "}"
                ]
              }
            },
            {
              "listen": "test",
              "script": {
                "type": "text/javascript",
                "exec": [
                  "pm.test('Status 200', () => pm.response.to.have.status(200));"
                ]
              }
            }
          ]
        }
      ]
    },
    {
      "name": "10 Cleanup",
      "item": [
        {
          "name": "DELETE /api/products/:id (omitido si vendido)",
          "request": {
            "method": "DELETE",
            "header": [
              {
                "key": "Content-Type",
                "value": "application/json",
                "disabled": false
              }
            ],
            "url": "{{baseUrl}}/api/products/{{flowProductId}}",
            "description": "",
            "auth": {
              "type": "bearer",
              "bearer": [
                {
                  "key": "token",
                  "value": "{{carlosToken}}",
                  "type": "string"
                }
              ]
            }
          },
          "event": [
            {
              "listen": "prerequest",
              "script": {
                "type": "text/javascript",
                "exec": [
                  "// Tras confirm-delivery el producto queda vendido y no se puede eliminar",
                  "pm.execution.skipRequest();"
                ]
              }
            }
          ]
        }
      ]
    }
  ]
}